alterclip-0.3.6.dist-info/licenses/LICENSE
web/app.py
alterclip-0.3.6.dist-info/METADATA
alterclip-0.3.6.dist-info/WHEEL
alterclip-0.3.6.dist-info/top_level.txt
alterclip-0.3.6.dist-info/RECORD
