Metadata-Version: 2.4
Name: alterclip
Version: 0.3.6
Summary: Herramienta para interceptar URLs desde el portapapeles y modificarlas o reproducirlas
Author-email: Julio Serrano <mhysterio@gmail.com>
License-Expression: GPL-3.0-only
Project-URL: Homepage, https://github.com/mhyst/alterclip
Requires-Python: >=3.8
License-File: LICENSE
Requires-Dist: pyperclip
Requires-Dist: plyer
Requires-Dist: platformdirs
Dynamic: license-file
